cnxdb/__init__.py
cnxdb/_version.py
cnxdb/config.py
cnxdb/scripting.py
cnxdb/archive-sql/README.shredding
cnxdb/archive-sql/create-db.sql
cnxdb/archive-sql/example_tree_col10522.json
cnxdb/archive-sql/get-available-languages-and-count.sql
cnxdb/archive-sql/get-book-core-info.sql
cnxdb/archive-sql/get-book-latest-version-with-page.sql
cnxdb/archive-sql/get-books-containing-page.sql
cnxdb/archive-sql/get-collated-content.sql
cnxdb/archive-sql/get-collated-state.sql
cnxdb/archive-sql/get-content-from-legacy-id-ver.sql
cnxdb/archive-sql/get-content-from-legacy-id.sql
cnxdb/archive-sql/get-core-info.sql
cnxdb/archive-sql/get-featured-links.sql
cnxdb/archive-sql/get-in-book-search-full-page.sql
cnxdb/archive-sql/get-in-book-search.sql
cnxdb/archive-sql/get-in-collated-book-search-full-page.sql
cnxdb/archive-sql/get-in-collated-book-search.sql
cnxdb/archive-sql/get-license-info-as-json.sql
cnxdb/archive-sql/get-module-head-version.sql
cnxdb/archive-sql/get-module-latest-version.sql
cnxdb/archive-sql/get-module-metadata.sql
cnxdb/archive-sql/get-module-uuid.sql
cnxdb/archive-sql/get-module-versions.sql
cnxdb/archive-sql/get-module.sql
cnxdb/archive-sql/get-resource-by-filename.sql
cnxdb/archive-sql/get-resource.sql
cnxdb/archive-sql/get-resourceid-by-filename.sql
cnxdb/archive-sql/get-service-state-messages.sql
cnxdb/archive-sql/get-subject-list.sql
cnxdb/archive-sql/get-tree-by-uuid-n-version.sql
cnxdb/archive-sql/get-users-by-ids.sql
cnxdb/archive-sql/query-collated_file_associations-by-xpath.sql
cnxdb/archive-sql/query-module_files-by-xpath.sql
cnxdb/archive-sql/schema_rename_proposal.txt
cnxdb/archive-sql/schema/README.md
cnxdb/archive-sql/schema/aggregates.sql
cnxdb/archive-sql/schema/common-functions.sql
cnxdb/archive-sql/schema/extensions.sql
cnxdb/archive-sql/schema/fulltext-indexing.sql
cnxdb/archive-sql/schema/functions.sql
cnxdb/archive-sql/schema/hits-functions.sql
cnxdb/archive-sql/schema/indexes.sql
cnxdb/archive-sql/schema/legacy_collxml.sql
cnx_db-3.5.3.dist-info/METADATA
cnx_db-3.5.3.dist-info/WHEEL
cnx_db-3.5.3.dist-info/entry_points.txt
cnx_db-3.5.3.dist-info/top_level.txt
cnx_db-3.5.3.dist-info/RECORD
