Metadata-Version: 2.1
Name: cnx-db
Version: 3.5.3
Summary: Connexions Database Library
Home-page: https://github.com/connexions/cnx-db
Author: Connexions team
Author-email: info@cnx.org
License: LGPL, See also LICENSE.txt
Platform: UNKNOWN
Requires-Dist: cnx-common (>=1.2.1)
Requires-Dist: cnx-transforms
Requires-Dist: psycopg2
Requires-Dist: sqlalchemy
Requires-Dist: requests
Requires-Dist: rhaptos.cnxmlutils
Requires-Dist: venusian
Requires-Dist: zope.deprecation (>=3.5.0)
Provides-Extra: test
Requires-Dist: pyramid ; extra == 'test'
Requires-Dist: pytest ; extra == 'test'
Requires-Dist: pytest-mock ; extra == 'test'
Requires-Dist: mock (==1.0.1) ; extra == 'test'
